functions/FOF.py
functions/Group_Summary.py
functions/__init__.py
functions/region_merging.py
functions/save_field.py
CNUFOF_utils-1.0.6.dist-info/METADATA
CNUFOF_utils-1.0.6.dist-info/WHEEL
CNUFOF_utils-1.0.6.dist-info/top_level.txt
CNUFOF_utils-1.0.6.dist-info/RECORD
