Metadata-Version: 2.1
Name: CNUFOF-utils
Version: 1.0.6
Summary: Parallalization Friends Of Friends based on observation data.
Home-page: https://github.com/dongyun-gwag
Author: Dongyun Kwak
Author-email: 98ehddbs@naver.com
License: MIT
Requires-Python: >= 3.9.18
Requires-Dist: ray
Requires-Dist: astropy
Requires-Dist: pandas
Requires-Dist: pydl
Requires-Dist: tqdm
